{"1": {"Prod_Name": "notebook", "MRP": 20, "Qty": 100, "Exp": "---"}, "2": {"Prod_Name": "science book", "MRP": 50, "Qty": 100, "Exp": "---"}, "3": {"Prod_Name": "PEN", "MRP": 10, "Qty": 100, "Exp": "---"}, "4": {"Prod_Name": "pencile", "MRP": 10, "Qty": 100, "Exp": "---"}, "5": {"Prod_Name": "drawing_box", "MRP": 50, "Qty": 40, "Exp": "---"}, "6": {"Prod_Name": "eraser box", "MRP": 50, "Qty": 50, "Exp": "---"}, "7": {"Prod_Name": "campas box", "MRP": 100, "Qty": 50, "Exp": "---"}, "8": {"Prod_Name": "writing pad", "MRP": 100, "Qty": 100, "Exp": "---"}, "9": {"Prod_Name": "school bags", "MRP": 250, "Qty": 30, "Exp": "---"}, "10": {"Prod_Name": "sketchpens", "MRP": 50, "Qty": 100, "Exp": "---"}}
